aap_langchain/__init__.py
aap_langchain/chain.py
aap_langchain/py.typed
aap_langchain/retriever.py
aap_langchain-0.1.2.dev1.dist-info/WHEEL
aap_langchain-0.1.2.dev1.dist-info/METADATA
aap_langchain-0.1.2.dev1.dist-info/RECORD
